DROPStomo/__init__.py
DROPStomo/WQPT1Q/WQPT1Q.py
DROPStomo/WQPT1Q/__init__.py
DROPStomo/WQST1Q/WQST1Q.py
DROPStomo/WQST1Q/__init__.py
DROPStomo/WQST2Q/WQST2Q.py
DROPStomo/WQST2Q/__init__.py
DROPStomo-0.0.6.dist-info/LICENSE
DROPStomo-0.0.6.dist-info/METADATA
DROPStomo-0.0.6.dist-info/WHEEL
DROPStomo-0.0.6.dist-info/top_level.txt
DROPStomo-0.0.6.dist-info/RECORD
